starlette_async_wstc/__init__.py
starlette_async_wstc/testclient.py
starlette_async_wstc-0.1.2.dist-info/LICENSE.md
starlette_async_wstc-0.1.2.dist-info/METADATA
starlette_async_wstc-0.1.2.dist-info/WHEEL
starlette_async_wstc-0.1.2.dist-info/top_level.txt
starlette_async_wstc-0.1.2.dist-info/RECORD
