Metadata-Version: 2.1
Name: starlette-async-wstc
Version: 0.1.2
Summary: Modification of Starlette TestClient to support async calls
Home-page: https://github.com/Randomneo/starlette_async_wstc
Author: Rostyslav Misiura
Author-email: rostislav9999@gmail.com
Maintainer: Rostyslav Misiura
Maintainer-email: rostislav9999@gmail.com
License: GNU Affero General Public License, version 3
Classifier: Intended Audience :: Developers
Classifier: License :: OSI Approved :: GNU General Public License v3 (GPLv3)
Classifier: Operating System :: OS Independent
Classifier: Programming Language :: Python :: 3
Classifier: Programming Language :: Python :: 3.10
Classifier: Programming Language :: Python :: 3.9
Classifier: Programming Language :: Python :: 3.8
Classifier: Programming Language :: Python :: 3.7
Classifier: Programming Language :: Python :: 3.6
License-File: LICENSE.md
Requires-Dist: starlette
Requires-Dist: requests
Requires-Dist: anyio
